igls/__init__.py
igls/main.py
igls-1.0.0.dist-info/LICENSE
igls-1.0.0.dist-info/METADATA
igls-1.0.0.dist-info/WHEEL
igls-1.0.0.dist-info/entry_points.txt
igls-1.0.0.dist-info/top_level.txt
igls-1.0.0.dist-info/RECORD
